MANIFEST.in
README.md
requirements.txt
setup.py
iam/__init__.py
iam/const.py
iam/canon/__init__.py
iam/canon/exc.py
iam/canon/dto/__init__.py
iam/canon/dto/realmconfig.py
iam/domain/__init__.py
iam/domain/abstractrealm.py
iam/domain/credential.py
iam/domain/emailprincipal.py
iam/domain/externalidentifierprincipal.py
iam/domain/facebookaccountprincipal.py
iam/domain/googleaccountprincipal.py
iam/domain/linkedinaccountprincipal.py
iam/domain/logincode.py
iam/domain/logincodecredential.py
iam/domain/mixins.py
iam/domain/nullcredential.py
iam/domain/nullprincipal.py
iam/domain/passwordcredential.py
iam/domain/phonenumberprincipal.py
iam/domain/principal.py
iam/domain/principalfactory.py
iam/domain/resource.py
iam/domain/resourcekind.py
iam/domain/resourceuuid.py
iam/domain/twitteraccountprincipal.py
iam/domain/tests/__init__.py
iam/domain/tests/test_emailprincipal_detect.py
iam/domain/tests/test_phonenumberprincipal_detect.py
iam/ext/__init__.py
iam/ext/app/__init__.py
iam/ext/app/settings.py
iam/ext/app/urls.py
iam/ext/app/tests/__init__.py
iam/ext/app/tests/test_happy_registration.py
iam/ext/django/__init__.py
iam/ext/django/apps.py
iam/ext/django/defaults.py
iam/ext/django/urls.py
iam/ext/django/admin/__init__.py
iam/ext/django/admin/acceptedplatformagreement.py
iam/ext/django/admin/platformagreementlanguage.py
iam/ext/django/admin/readonly.py
iam/ext/django/admin/subjectregistration.py
iam/ext/django/fixtures/testusers.yaml
iam/ext/django/infra/__init__.py
iam/ext/django/infra/hashedpasswordrepository.py
iam/ext/django/infra/subjectrepository.py
iam/ext/django/jinja2/iam/debug.html.j2
iam/ext/django/jinja2/iam/login.completenames.html.j2
iam/ext/django/jinja2/iam/login.html.j2
iam/ext/django/jinja2/iam/login.magic.html.j2
iam/ext/django/jinja2/iam/login.passwordexpired.html.j2
iam/ext/django/jinja2/iam/login.token.html.j2
iam/ext/django/jinja2/iam/login.useragreement.html.j2
iam/ext/django/jinja2/iam/login.useragreement.privacy.html.j2
python_iam.egg-info/PKG-INFO
python_iam.egg-info/SOURCES.txt
python_iam.egg-info/dependency_links.txt
python_iam.egg-info/requires.txt
python_iam.egg-info/top_level.txt